{
    "name": "local_ganache",

    "network": {
        "type": "ganache",
        "host": "127.0.0.1",
        "port": 8545,
        "protocol": "http",
        "network_id": 2702,

        "config": {
            "mnemonic": "cross uniform panic climb universe awful surprise list dutch ability label cat",
            "image": "trufflesuite/ganache-cli",
            "version": "latest",
            "container_name": "t721-ethnode",
            "gasLimit": "8000000",
            "gasPrice": "0x2540BE400"
        }

    },

    "dev": {
        "vaultereumHost": "127.0.0.1",
        "vaultereumPort": 8200,
        "vaultereumProtocol": "http",
        "vaultereumEthHost": "ganache",
        "vaultereumEthPort": 8545,
        "vaultereumEthProtocol": "http",
        "vaultereumEthNetId": 2702,
        "vaultereumToken": "dev_root_token",
        "extraAdmins": [
            "0xea51bf51cdd20b0b7a65623992ecf516bb03a082"
        ],
        "extraAdminsEth": "1",
        "t721adminFunds": "10"
    },

    "contracts": {
        "migrations": [
            {
                "name": "initial_deployment",
                "serie": [
                    {
                        "name": "daiplus",
                        "test": false,
                        "range": [1, 2],
                        "args": {
                            "ERC20": {
                                "name": "DaiPlus Local Meta-Stablecoin v1.0",
                                "symbol": "Dai+",
                                "decimals": 18
                            }
                        }
                    },
                    {
                        "name": "ticketforge",
                        "test": false,
                        "range": [1, 2],
                        "args": {
                            "ERC721": {
                                "name": "Ticket Forge",
                                "symbol": "TKT"
                            }
                        }
                    },
                    {
                        "name": "metamarketplace",
                        "test": false,
                        "range": [1, 2]
                    },
                    {
                        "name": "t721controller",
                        "test": false,
                        "range": [1, 2]
                    },
                    {
                        "name": "refract",
                        "test": false,
                        "range": [1, 2]
                    },
                    {
                        "name": "t721token",
                        "test": false,
                        "range": [1, 1]
                    }
                ]
            }
        ],
        "modules": [
            {
                "name": "daiplus",
                "upgradeable": false
            },
            {
                "name": "ticketforge",
                "upgradeable": false
            },
            {
                "name": "metamarketplace",
                "upgradeable": false
            },
            {
                "name": "t721controller",
                "upgradeable": false
            },
            {
                "name": "refract",
                "upgradeable": false
            },
            {
                "name": "t721token",
                "upgradeable": false
            }
        ],
        "provider": {
            "type": "hdwallet",
            "mnemonic": "cross uniform panic climb universe awful surprise list dutch ability label cat",
            "account_index": 0,
            "account_number": 10
        }
    }

}
